LICENSE
README.rst
microsky.py
setup.py
microsky.egg-info/PKG-INFO
microsky.egg-info/SOURCES.txt
microsky.egg-info/dependency_links.txt
microsky.egg-info/requires.txt
microsky.egg-info/top_level.txt